zephcast/__init__.py
zephcast/aio/__init__.py
zephcast/aio/base.py
zephcast/aio/consumers.py
zephcast/aio/kafka/__init__.py
zephcast/aio/kafka/client.py
zephcast/aio/kafka/types.py
zephcast/aio/rabbit/__init__.py
zephcast/aio/rabbit/client.py
zephcast/aio/rabbit/types.py
zephcast/aio/redis/__init__.py
zephcast/aio/redis/client.py
zephcast/aio/redis/types.py
zephcast/aio/retry.py
zephcast/core/__init__.py
zephcast/core/consumers.py
zephcast/core/exceptions.py
zephcast/core/factory.py
zephcast/core/retry.py
zephcast/core/types.py
zephcast/core/utils.py
zephcast/sync/__init__.py
zephcast/sync/base.py
zephcast/sync/consumers.py
zephcast/sync/kafka/__init__.py
zephcast/sync/kafka/client.py
zephcast/sync/kafka/types.py
zephcast/sync/rabbit/__init__.py
zephcast/sync/rabbit/client.py
zephcast/sync/rabbit/types.py
zephcast/sync/redis/__init__.py
zephcast/sync/redis/client.py
zephcast/sync/redis/types.py
zephcast/sync/retry.py
zephcast/testing/__init__.py
zephcast/testing/aio/__init__.py
zephcast/testing/aio/mock_client.py
zephcast/testing/factory.py
zephcast/testing/helpers.py
zephcast/testing/mock_client.py
zephcast/testing/sync/__init__.py
zephcast/testing/sync/mock_client.py
zephcast-0.6.0.dist-info/LICENSE
zephcast-0.6.0.dist-info/METADATA
zephcast-0.6.0.dist-info/WHEEL
zephcast-0.6.0.dist-info/RECORD
