Metadata-Version: 2.1
Name: zephcast
Version: 0.6.0
Summary: A messaging library supporting multiple backends
Author: Zbigniew Mastylo
Author-email: z.mastylo@protonmail.com
Requires-Python: >=3.10,<4.0
Classifier: Programming Language :: Python :: 3
Classifier: Programming Language :: Python :: 3.10
Classifier: Programming Language :: Python :: 3.11
Classifier: Programming Language :: Python :: 3.12
Provides-Extra: aio
Provides-Extra: all
Provides-Extra: async
Provides-Extra: async-kafka
Provides-Extra: async-rabbit
Provides-Extra: async-redis
Provides-Extra: kafka
Provides-Extra: rabbit
Provides-Extra: redis
Provides-Extra: sync
Provides-Extra: sync-kafka
Provides-Extra: sync-rabbit
Provides-Extra: sync-redis
Requires-Dist: aio-pika (>=9.3.1,<10.0.0) ; extra == "async" or extra == "aio" or extra == "async-rabbit" or extra == "rabbit" or extra == "all"
Requires-Dist: aiokafka (>=0.10.0,<0.11.0) ; extra == "async" or extra == "aio" or extra == "async-kafka" or extra == "kafka" or extra == "all"
Requires-Dist: aioredis (>=2.0.1,<3.0.0) ; extra == "async" or extra == "aio" or extra == "async-redis" or extra == "redis" or extra == "all"
Requires-Dist: kafka-python (>=2.0.2,<3.0.0) ; extra == "sync" or extra == "sync-kafka" or extra == "kafka" or extra == "all"
Requires-Dist: pika (>=1.3.2,<2.0.0) ; extra == "sync" or extra == "sync-rabbit" or extra == "rabbit" or extra == "all"
Requires-Dist: redis (>=5.0.1,<6.0.0) ; extra == "sync" or extra == "sync-redis" or extra == "redis" or extra == "all"
Requires-Dist: typing-extensions (>=4.8.0,<5.0.0)
